nagogy/__init__.py
nagogy/nagogy.py
nagogy-1.1.0.dist-info/METADATA
nagogy-1.1.0.dist-info/WHEEL
nagogy-1.1.0.dist-info/top_level.txt
nagogy-1.1.0.dist-info/RECORD
