Metadata-Version: 2.1
Name: nagogy
Version: 1.1.0
Summary: normal nagie
Author: dynastyoak
Author-email: nagogy@gmail.com
Keywords: python
Classifier: Programming Language :: Python :: 3
Classifier: Operating System :: Microsoft :: Windows
